inference_sdk/__init__.py
inference_sdk/config.py
inference_sdk/version.py
inference_sdk/http/__init__.py
inference_sdk/http/client.py
inference_sdk/http/entities.py
inference_sdk/http/errors.py
inference_sdk/http/utils/__init__.py
inference_sdk/http/utils/aliases.py
inference_sdk/http/utils/encoding.py
inference_sdk/http/utils/executors.py
inference_sdk/http/utils/iterables.py
inference_sdk/http/utils/loaders.py
inference_sdk/http/utils/post_processing.py
inference_sdk/http/utils/pre_processing.py
inference_sdk/http/utils/profilling.py
inference_sdk/http/utils/request_building.py
inference_sdk/http/utils/requests.py
inference_sdk/utils/__init__.py
inference_sdk/utils/decorators.py
inference_sdk/utils/environment.py
inference_sdk/utils/logging.py
inference_sdk/webrtc/__init__.py
inference_sdk/webrtc/client.py
inference_sdk/webrtc/config.py
inference_sdk/webrtc/datachannel.py
inference_sdk/webrtc/session.py
inference_sdk/webrtc/sources.py
inference_sdk-0.64.6.dist-info/licenses/LICENSE
inference_sdk-0.64.6.dist-info/licenses/LICENSE.core
inference_sdk-0.64.6.dist-info/METADATA
inference_sdk-0.64.6.dist-info/WHEEL
inference_sdk-0.64.6.dist-info/top_level.txt
inference_sdk-0.64.6.dist-info/RECORD
